datashard/__init__.py
datashard/__main__.py
datashard/avro_schemas.py
datashard/data_operations.py
datashard/data_structures.py
datashard/disk_utils.py
datashard/file_lock.py
datashard/file_manager.py
datashard/filters.py
datashard/garbage_collector.py
datashard/iceberg.py
datashard/integrity.py
datashard/lock_provider.py
datashard/logging_config.py
datashard/metadata_manager.py
datashard/s3_consistency.py
datashard/snapshot_manager.py
datashard/storage_backend.py
datashard/transaction.py
datashard-0.5.4.dist-info/licenses/LICENSE
datashard-0.5.4.dist-info/METADATA
datashard-0.5.4.dist-info/WHEEL
datashard-0.5.4.dist-info/top_level.txt
datashard-0.5.4.dist-info/RECORD
