Metadata-Version: 2.4
Name: datashard
Version: 0.5.4
Summary: Safe concurrent data operations for ML/AI workloads, Python implementation of Apache Iceberg concepts with S3 support
Author-email: RODMENA LIMITED <contact@rodmena.com>
License-Expression: Apache-2.0
Project-URL: Homepage, https://github.com/rodmena-limited/datashard
Project-URL: Repository, https://github.com/rodmena-limited/datashard
Project-URL: Documentation, https://datashard.readthedocs.io/
Classifier: Development Status :: 3 - Alpha
Classifier: Intended Audience :: Developers
Classifier: Intended Audience :: Science/Research
Classifier: Operating System :: OS Independent
Classifier: Programming Language :: Python :: 3
Classifier: Programming Language :: Python :: 3.7
Classifier: Programming Language :: Python :: 3.8
Classifier: Programming Language :: Python :: 3.9
Classifier: Programming Language :: Python :: 3.10
Classifier: Programming Language :: Python :: 3.11
Classifier: Programming Language :: Python :: 3.12
Classifier: Programming Language :: Python :: 3.13
Classifier: Programming Language :: Python :: 3.14
Classifier: Topic :: Database
Classifier: Topic :: Scientific/Engineering
Classifier: Topic :: Software Development :: Libraries :: Python Modules
Requires-Python: >=3.7
License-File: LICENSE
Requires-Dist: pyarrow>=10.0.0
Requires-Dist: lz4>=4.0.0
Requires-Dist: fastavro>=1.4.0
Requires-Dist: typing-extensions>=3.10.0; python_version < "3.10"
Provides-Extra: s3
Requires-Dist: boto3>=1.26.0; extra == "s3"
Provides-Extra: pandas
Requires-Dist: pandas>=1.3.0; extra == "pandas"
Provides-Extra: dev
Requires-Dist: pytest>=7.0; extra == "dev"
Requires-Dist: pytest-cov>=4.0; extra == "dev"
Requires-Dist: pytest-xdist>=3.0; extra == "dev"
Requires-Dist: black>=22.0; extra == "dev"
Requires-Dist: ruff>=0.0.247; extra == "dev"
Requires-Dist: isort>=5.0; extra == "dev"
Requires-Dist: mypy>=1.0; extra == "dev"
Requires-Dist: types-setuptools>=65.0; extra == "dev"
Requires-Dist: boto3>=1.26.0; extra == "dev"
Provides-Extra: docs
Requires-Dist: sphinx>=4.0; extra == "docs"
Requires-Dist: sphinx-rtd-theme>=1.0; extra == "docs"
Requires-Dist: sphinx-autodoc-typehints>=1.0; extra == "docs"
Dynamic: license-file
